{
  "parent": "minecraft:adventure/root",
  "display": {
    "icon": {
      "item": "minecraft:cauldron"
    },
    "title": {
      "translate": "advancements.moreadvancementsmod.adventure.find_witch_hut.title"
    },
    "description": {
      "translate": "advancements.moreadvancementsmod.adventure.find_witch_hut.description"
    },
    "frame": "goal",
    "show_toast": true,
    "announce_to_chat": true,
    "hidden": false
  },
  "criteria": {
    "requirement": {
      "conditions": {
        "player": [
          {
            "condition": "minecraft:entity_properties",
            "entity": "this",
            "predicate": {
              "location": {
                "structure": "minecraft:swamp_hut"
              }
            }
          }
        ]
      },
      "trigger": "minecraft:location"
    }
       }}